composition_if/mock_pred.v
module mock_pred(RST, ST, CLK, RD, RES, IN1, IN2, IN3);
   input wire RST;
   input wire ST;
   input wire CLK;
   output reg RD;
   output reg [16-1:0] RES;
   input wire [16-1:0] IN1;
   input wire [16-1:0] IN2;
   input wire [16-1:0] IN3;
   reg [3:0] 		   CNT;
   
   always @(posedge CLK) begin
	  if(RST == 1) begin
		 RD = 1;
		 RES = 0;
		 CNT = 0;
	  end else begin
		 if (ST == 1 && RD == 1) begin
			RD = 0;
			CNT = 2;			
		 end else if (CNT > 0) begin
			CNT = CNT - 1;
		 end else begin
			RD = 1;
		 end
		 RES = 1;
	  end	  	  
   end
endmodule // mock_yes

composition_if/mock_no.v
module mock_no(RST, ST, CLK, RD, RES, IN1, IN2, IN3);
   input wire RST;
   input wire ST;
   input wire CLK;
   output reg RD;
   output reg [16-1:0] RES;
   input wire [16-1:0] IN1;
   input wire [16-1:0] IN2;
   input wire [16-1:0] IN3;
   reg [3:0] 		   CNT;
   
   always @(posedge CLK) begin
	  if(RST == 1) begin
		 RD = 1;
		 RES = 0;
		 CNT = 0;
	  end else begin
		 if (ST == 1 && RD == 1) begin
			RD = 0;
			CNT = 2;			
		 end else if (CNT > 0) begin
			CNT = CNT - 1;
		 end else begin
			RD = 1;
		 end
		 RES = 2;
	  end	  	  
   end
endmodule // mock_yes

composition_if/mock_yes.v
module mock_yes(RST, ST, CLK, RD, RES, IN1, IN2, IN3);
   input wire RST;
   input wire ST;
   input wire CLK;
   output reg RD;
   output reg [16-1:0] RES;
   input wire [16-1:0] IN1;
   input wire [16-1:0] IN2;
   input wire [16-1:0] IN3;
   reg [3:0] 		   CNT;
   
   always @(posedge CLK) begin
	  if(RST == 1) begin
		 RD = 1;
		 RES = 0;
		 CNT = 0;
	  end else begin
		 if (ST == 1 && RD == 1) begin
			RD = 0;
			CNT = 4;			
		 end else if (CNT > 0) begin
			CNT = CNT - 1;
		 end else begin
			RD = 1;
		 end
		 RES = 2;
	  end	  	  
   end
endmodule // mock_yes

composition_if/composition_if.v
module modulename(
				  RST, 
				  ST,
				  CLK,
				  RD,
				  RES,
				  IN1,
				  IN2,
				  IN3
				  );
   input wire          RST;
   input wire          ST;
   input wire          CLK;
   output reg          RD;
   output reg [16-1:0] RES;
   input wire [16-1:0] IN1;
   input wire [16-1:0] IN2;
   input wire [16-1:0] IN3;
   reg [3:0] 		   state;
   wire [16-1:0] 	   SOUT_YES;
   wire [16-1:0] 	   SOUT_NO;
   wire [16-1:0] 	   pRES;
   wire [16-1:0] 	   lRES; 	   
   wire 			   yRD;
   wire 			   nRD;
   wire 			   pRD;
   wire 			   lRD;
   reg 				   yST;
   reg 				   nST;
   reg  			   pST;

   assign lRD = nRD & yRD & pRD;
   assign lRES = pRES > 0?SOUT_YES:SOUT_NO;
   mock_yes yes(RST, yST, CLK, yRD, SOUT_YES, IN1, IN2, IN3);
   mock_no no(RST, nST, CLK, nRD, SOUT_NO, IN1, IN2, IN3);
   mock_pred pred(RST, pST, CLK, pRD, pRES, IN1, IN2, IN3);

   always @(posedge CLK) begin
	  if (RST == 1) begin
		 yST = 0;
		 nST = 0;
		 pST = 0;
		 state = 0;
		 RD = 1;
		 RES = 0;		
	  end
	  case (state)
		0:begin
		   RD = 1;
		   if (ST == 1) state = 1;
		end
		1:begin
		   yST = 1;
		   nST = 1;
		   pST = 1;
		   RD = 0;
		   state = 2;
		end
		2:begin
		   state = 3;
		end
		3:begin
		   yST = 0;
		   nST = 0;
		   pST = 0;
		   if (lRD == 1) state = 4;		   
		end
		4:begin
		   RD = 1;
		   RES = lRES;
		   state = 5;
		end
		5:begin
		   RD = 1;
		   if(ST == 1) state = 1;
		end
	  endcase // case (state)
   end // always @ (posedge CLK)
endmodule // modulename

composition_if/if_testbench.v
module fortestbench();
   wire RST;
   reg 	rRST;
   wire CLK;
   reg 	rCLK;
   wire ST;
   reg 	rST;
   wire [16-1:0] IN1;
   wire [16-1:0] IN2;
   wire [16-1:0] IN3;
   reg [16-1:0]  rIN1;
   reg [16-1:0]  rIN2;
   reg [16-1:0]  rIN3;
   wire [16-1:0] RES;
   wire 		 RD;
   
   assign RST = rRST;
   assign ST = rST;
   assign CLK = rCLK;
   assign IN1 = rIN1;
   assign IN2 = rIN2;
   assign IN3 = rIN3;
   
   modulename dut(RST, ST, CLK, RD, RES, IN1, IN2, IN3);
   
   initial rCLK = 0;
   always #5 rCLK = ~rCLK;
   
   initial begin
	  $dumpfile("result.vcd");
	  $dumpvars;
	  rIN1 = 5;
	  rIN2 = 4;
	  rIN3 = 3;
	  rRST = 1;
	  #20 rRST = 0;
	  rST = 1;
	  #20 rST = 0;
	  #2000
	  $finish;
   end
 
   
endmodule // fortestbench

composition_if/result.vcd
$date
	Sun Jan 12 22:28:52 2014
$end
$version
	Icarus Verilog
$end
$timescale
	1s
$end
$scope module fortestbench $end
$var wire 1 ! CLK $end
$var wire 16 " IN1 [15:0] $end
$var wire 16 # IN2 [15:0] $end
$var wire 16 $ IN3 [15:0] $end
$var wire 1 % RD $end
$var wire 16 & RES [15:0] $end
$var wire 1 ' RST $end
$var wire 1 ( ST $end
$var reg 1 ) rCLK $end
$var reg 16 * rIN1 [15:0] $end
$var reg 16 + rIN2 [15:0] $end
$var reg 16 , rIN3 [15:0] $end
$var reg 1 - rRST $end
$var reg 1 . rST $end
$scope module dut $end
$var wire 1 ! CLK $end
$var wire 16 / IN1 [15:0] $end
$var wire 16 0 IN2 [15:0] $end
$var wire 16 1 IN3 [15:0] $end
$var wire 1 ' RST $end
$var wire 16 2 SOUT_NO [15:0] $end
$var wire 16 3 SOUT_YES [15:0] $end
$var wire 1 ( ST $end
$var wire 1 4 lRD $end
$var wire 16 5 lRES [15:0] $end
$var wire 1 6 nRD $end
$var wire 1 7 pRD $end
$var wire 16 8 pRES [15:0] $end
$var wire 1 9 yRD $end
$var reg 1 : RD $end
$var reg 16 ; RES [15:0] $end
$var reg 1 < nST $end
$var reg 1 = pST $end
$var reg 4 > state [3:0] $end
$var reg 1 ? yST $end
$scope module yes $end
$var wire 1 ! CLK $end
$var wire 16 @ IN1 [15:0] $end
$var wire 16 A IN2 [15:0] $end
$var wire 16 B IN3 [15:0] $end
$var wire 1 ' RST $end
$var wire 1 C ST $end
$var reg 4 D CNT [3:0] $end
$var reg 1 E RD $end
$var reg 16 F RES [15:0] $end
$upscope $end
$scope module no $end
$var wire 1 ! CLK $end
$var wire 16 G IN1 [15:0] $end
$var wire 16 H IN2 [15:0] $end
$var wire 16 I IN3 [15:0] $end
$var wire 1 ' RST $end
$var wire 1 J ST $end
$var reg 4 K CNT [3:0] $end
$var reg 1 L RD $end
$var reg 16 M RES [15:0] $end
$upscope $end
$scope module pred $end
$var wire 1 ! CLK $end
$var wire 16 N IN1 [15:0] $end
$var wire 16 O IN2 [15:0] $end
$var wire 16 P IN3 [15:0] $end
$var wire 1 ' RST $end
$var wire 1 Q ST $end
$var reg 4 R CNT [3:0] $end
$var reg 1 S RD $end
$var reg 16 T RES [15:0] $end
$upscope $end
$upscope $end
$upscope $end
$enddefinitions $end
#0
$dumpvars
bx T
xS
bx R
xQ
b11 P
b100 O
b101 N
bx M
xL
bx K
xJ
b11 I
b100 H
b101 G
bx F
xE
bx D
xC
b11 B
b100 A
b101 @
x?
bx >
x=
x<
bx ;
x:
x9
bx 8
x7
x6
bx 5
x4
bx 3
bx 2
b11 1
b100 0
b101 /
x.
1-
b11 ,
b100 +
b101 *
0)
x(
1'
bx &
x%
b11 $
b100 #
b101 "
0!
$end
#5
14
b0 5
b0 D
b0 F
b0 3
1E
19
b0 K
b0 M
b0 2
1L
16
b0 R
b0 T
b0 8
1S
17
b0 ;
b0 &
1:
1%
b0 >
0=
0Q
0<
0J
0?
0C
1)
1!
#10
0)
0!
#15
1)
1!
#20
0)
0!
1.
1(
0-
0'
#25
b10 5
b10 F
b10 3
b10 M
b10 2
b1 T
b1 8
b1 >
1)
1!
#30
0)
0!
#35
b10 >
0:
0%
1=
1Q
1<
1J
1?
1C
1)
1!
#40
0)
0!
0.
0(
#45
04
b100 D
0E
09
b10 K
0L
06
b10 R
0S
07
b11 >
1)
1!
#50
0)
0!
#55
0=
0Q
0<
0J
0?
0C
b1 R
b1 K
b11 D
1)
1!
#60
0)
0!
#65
b10 D
b0 K
b0 R
1)
1!
#70
0)
0!
#75
1S
17
1L
16
b1 D
1)
1!
#80
0)
0!
#85
b0 D
1)
1!
#90
0)
0!
#95
14
1E
19
1)
1!
#100
0)
0!
#105
b100 >
1)
1!
#110
0)
0!
#115
b101 >
b10 ;
b10 &
1:
1%
1)
1!
