multiplication/operation_i_bw16_inc2_si0.v
module operation_i_bw16_inc2_si0(RST, ST, CLK, RD, RES, IN0, IN1);
	input wire RST;
	input wire ST;
	input wire CLK;
	output reg RD;
	output reg [16-1:0] RES;
	reg STold;
	reg RF;
	input wire [15:0] IN0;
	input wire [15:0] IN1;


	always @(posedge CLK) begin
		if(RST == 1) begin
			RD = 1;
		end else begin
			if(RF == 1) begin
				RD = 1;
			end
			if(RF == 0) begin
				RES = IN0;
				RF = 1;
			end
			if(ST == 1 && STold == 0) begin
                                RD = 0;
				RF = 0;
                        end
		end
		if(ST == 1) begin
			STold = 1;
		end else begin
			STold = 0;
		end
	end	
endmodule

addition/operation_s_bw16.v
module operation_s_bw16(RST, ST, CLK, RD, RES, IN);
	input wire RST;
	input wire ST;
	input wire CLK;
	output reg RD;
	output reg [16-1:0] RES;
	input wire [16-1:0] IN;
	reg STold;
	reg RF;
	always @(posedge CLK) begin
		if(RST == 1) begin
			RD = 1;
			RF = 1;
		end else begin
			if(RF == 1) begin
				RD = 1;
			end
			if(RF == 0) begin
				RES = IN + 1;
				RF = 1;
			end
			if(ST == 1 && STold == 0) begin
                                RF = 0;
				RD = 0;
                        end
		end
		STold = ST;
	end	
endmodule

multiplication/operation_i_bw16_inc3_si2.v
module operation_i_bw16_inc3_si2(RST, ST, CLK, RD, RES, IN0, IN1, IN2);
	input wire RST;
	input wire ST;
	input wire CLK;
	output reg RD;
	output reg [16-1:0] RES;
	reg STold;
	reg RF;
	input wire [15:0] IN0;
	input wire [15:0] IN1;
	input wire [15:0] IN2;


	always @(posedge CLK) begin
		if(RST == 1) begin
			RD = 1;
			RF = 1;
		end else begin
			if(RF == 1) begin 
				RD = 1;
			end
			if(RF == 0) begin
				RES = IN2;
				RF = 1;
			end
			if(ST == 1 && STold == 0) begin
                                RF = 0;
				RD = 0;
                        end
		end
		STold = ST;
	end	
endmodule

multiplication/addition_func_h.v
module addition_func_h(RST, ST, CLK, RD, RES, IN0, IN1, IN2);
	input wire RST;
	input wire ST;
	input wire CLK;
	output wire RD;
	output wire [15:0] RES;
	input wire [15:0] IN0;
	input wire [15:0] IN1;
	input wire [15:0] IN2;
	wire [15:0] RESi;
	wire  RDi;
	
	operation_i_bw16_inc3_si2 opi3(RST, ST, CLK, RDi, RESi, IN0, IN1, IN2);
	operation_s_bw16 soperation(RST, RDi, CLK, RD, RES, RESi);	
	
endmodule

addition/operation_i_bw16_inc2_si1.v
module operation_i_bw16_inc2_si1(RST, ST, CLK, RD, RES, IN0, IN1);
	input wire RST;
	input wire ST;
	input wire CLK;
	output reg RD;
	output reg [16-1:0] RES;
	reg STold;
	reg RF;
	input wire [15:0] IN0;
	input wire [15:0] IN1;


	always @(posedge CLK) begin
		if(RST == 1) begin
			RD = 1;
			RF = 1;
		end else begin
			if(RF == 1) begin
				RD = 1;
			end
			if(RF == 0) begin
				RES = IN1;
				RF = 1;
			end
			if(ST == 1 && STold == 0) begin
                                RD = 0;
				RF = 0;
                        end
		end
		STold = ST;
	end	
endmodule

multiplication/composition_r_goperation_i_bw16_inc2_si1_haddition_func_h_bw_16_icnt2.v
module composition_r_goperation_i_bw16_inc2_si1_haddition_func_h_bw_16_icnt2(RST, ST, CLK, RD, RES, IN0, IN1);
	input wire RST;
	input wire ST;
	input wire CLK;
	output reg RD;
	output reg [16-1:0] RES;
	reg [16-1:0] BUF;
	wire [16-1:0] res_g;
	wire [16-1:0] res_h;
	reg [16-1:0] CNT;
	reg [16-1:0] ITERATIONS;
	wire rd_g;
	wire rd_h;
	reg st_h;
	reg st_h_f;
	reg STold;
	reg rd_g_old;
	reg rd_h_old;
	
	input wire [16-1:0] IN0;
	input wire [16-1:0] IN1;
	wire [16-1:0] IN2;
	
	operation_i_bw16_inc2_si1 g(RST, ST, CLK, rd_g, res_g, IN1, IN0);
	addition_func_h h(RST, st_h, CLK, rd_h, res_h, IN0, IN1, IN2);
	//g, h
	
	assign IN2[15:0] = (CNT[15:0] > 1)?res_h[15:0]:res_g[15:0];

	always @(posedge CLK) begin
		if(RST == 1) begin
			RD = 1;
			CNT = 0;
			STold = 0;
			rd_g_old = 0;
			rd_h_old = 0;
			st_h_f = 0;
			st_h = 0;
		end else begin
			if(ITERATIONS == CNT && rd_g == 1) begin
                        	RD = 1;
				CNT = 0;
				st_h = 0;
				st_h_f = 0;
				if(ITERATIONS == 0) begin
					RES = res_g;
				end else begin
					RES = BUF;
				end
			end

			if(RD == 0) begin
				if(st_h_f == 0) begin
                                        st_h = 0;
                                end
                                if(st_h == 1) begin
                                        st_h_f = 0;
                                end
				if(rd_g == 1 && rd_g_old == 0 && CNT == 0) begin
					BUF = res_g;
					st_h_f = 1;
					st_h = 1;
				end
				if(rd_h == 1 && rd_h_old == 0) begin
					BUF = res_h;
					CNT = CNT + 1;
                                        st_h_f = 1;
                                        st_h = 1;
				end
					
			end
			if(ST == 1 && STold == 0) begin
				RD = 0;
				if(IN1 > 0) begin
					ITERATIONS = IN1 + 1;
				end else begin
					ITERATIONS = 0;
				end
			end
		end
		if(ST == 1) begin
			STold = 1;
		end else begin 
			STold = 0;
		end
		rd_g_old = rd_g;
		rd_h_old = rd_h;
	end
endmodule

multiplication/multiplication_func_h.v
module multiplication_func_h(RST, ST, CLK, RD, RES, IN0, IN1, IN2);
	input wire RST;
	input wire ST;
	input wire CLK;
	output wire RD;
	output wire [15:0] RES;
	input wire [15:0] IN0;
	input wire [15:0] IN1;
	input wire [15:0] IN2;
	
	composition_r_goperation_i_bw16_inc2_si1_haddition_func_h_bw_16_icnt2 summa(RST, ST, CLK, RD, RES, IN0, IN2);	
	
endmodule

multiplication/operation_o_bw16_inc2.v
module operation_o_bw16_inc2(RST, ST, CLK, RD, RES, IN0, IN1);
	input wire RST;
	input wire ST;
	input wire CLK;
	output reg RD;
	output reg [16-1:0] RES;
	reg STold;
	reg RF;
	input wire [15:0] IN0;
	input wire [15:0] IN1;


	always @(posedge CLK) begin
		if(RST == 1) begin
			RD = 1;
		end else begin
			if(RF == 1) begin
				RD = 1;
			end
			if(RF == 0) begin
				RES = 0;
				RF = 1;
			end
			if(ST == 1 && STold == 0) begin
                                RD = 0;
                     		RF = 0;
			   end
		end
		STold = ST;
	end	
endmodule

multiplication/composition_r_goperation_o_bw16_inc2_hmultiplication_func_h_bw_16_icnt2.v
module composition_r_goperation_o_bw16_inc2_hmultiplication_func_h_bw_16_icnt2(RST, ST, CLK, RD, RES, IN0, IN1);
	input wire RST;
	input wire ST;
	input wire CLK;
	output reg RD;
	output reg [16-1:0] RES;
	reg [16-1:0] BUF;
	wire [16-1:0] res_g;
	wire [16-1:0] res_h;
	reg [16-1:0] CNT;
	reg [16-1:0] ITERATIONS;
	wire rd_g;
	wire rd_h;
	reg st_h;
	reg st_h_f;
	reg STold;
	reg rd_g_old;
	reg rd_h_old;
	
	input wire [16-1:0] IN0;
	input wire [16-1:0] IN1;
	wire [16-1:0] IN2;
	
	operation_o_bw16_inc2 g(RST, ST, CLK, rd_g, res_g, IN0, IN1);
	multiplication_func_h h(RST, st_h, CLK, rd_h, res_h, IN0, IN1, IN2);
	//g, h

	assign IN2[16-1:0] = (CNT[16-1:0] > 1)?res_h[16-1:0]:res_g[16-1:0];

	always @(posedge CLK) begin
		if(RST == 1) begin
			RD = 1;
			CNT = 0;
			STold = 0;
			rd_g_old = 0;
			rd_h_old = 0;
			st_h_f = 0;
			st_h = 0;
		end else begin
			if(ITERATIONS == CNT && rd_g == 1) begin
				RD = 1;
				CNT = 0;
				st_h = 0;
				st_h_f = 0;
				if(ITERATIONS == 0) begin
                                        RES = res_g;
                                end else begin
                                        RES = BUF;
                                end
			end

			if(RD == 0) begin
				if(st_h_f == 0) begin
					st_h = 0;
				end
				if(st_h == 1) begin
					st_h_f = 0;
				end
				if(rd_g == 1 && rd_g_old == 0 && CNT == 0) begin
					BUF = res_g;
					st_h_f = 1;
					st_h = 1;
				end
				if(rd_h == 1 && rd_h_old == 0) begin
					BUF = res_h;
					CNT = CNT + 1;
					st_h_f = 1;
					st_h = 1;
				end
					
			end
			if(ST == 1 && STold == 0) begin
				RD = 0;
				if(IN1 > 0) begin
                                        ITERATIONS = IN1 + 1;
                                end else begin
                                        ITERATIONS = 0;
                                end
			end
		end
		if(ST == 1) begin
			STold = 1;
		end else begin
			STold = 0;
		end
		rd_g_old = rd_g;
		rd_h_old = rd_h;
	end
endmodule

multiplication/multiplication_tb.v
module multiplication_tb;
	wire CLK;
	reg rCLK;
	wire RST;
	reg rRST;
	wire ST;
	reg rST;
	wire RD;
	wire [16-1:0] RES;
	wire [15:0] IN0;
	wire [15:0] IN1;

	reg [15:0] rIN0;
	reg [15:0] rIN1;
	
	composition_r_goperation_o_bw16_inc2_hmultiplication_func_h_bw_16_icnt2 op_m(RST, ST, CLK, RD, RES, IN0, IN1);

	assign CLK = rCLK;
	assign ST = rST;
	assign RST = rRST;
	assign IN0 = rIN0;
	assign IN1 = rIN1;

	initial begin
		$dumpfile("addition_tb.vcd");
		$dumpvars;
		rCLK = 0;
		rRST = 1;
		rST = 0;
		rIN0 = 4;
		rIN1 = 5;
		#15 rRST = 0;
		#10 rST = 1;
		#10 rST = 0;
		#4000 $finish;
	end


	always #5 rCLK = !rCLK;
	
endmodule

multiplication/addition_tb.vcd
$date
	Wed Jun  5 20:20:03 2013
$end
$version
	Icarus Verilog
$end
$timescale
	1s
$end
$scope module multiplication_tb $end
$var wire 1 ! CLK $end
$var wire 16 " IN0 [15:0] $end
$var wire 16 # IN1 [15:0] $end
$var wire 1 $ RD $end
$var wire 16 % RES [15:0] $end
$var wire 1 & RST $end
$var wire 1 ' ST $end
$var reg 1 ( rCLK $end
$var reg 16 ) rIN0 [15:0] $end
$var reg 16 * rIN1 [15:0] $end
$var reg 1 + rRST $end
$var reg 1 , rST $end
$scope module op_m $end
$var wire 1 ! CLK $end
$var wire 16 - IN0 [15:0] $end
$var wire 16 . IN1 [15:0] $end
$var wire 16 / IN2 [15:0] $end
$var wire 1 & RST $end
$var wire 1 ' ST $end
$var wire 1 0 rd_g $end
$var wire 1 1 rd_h $end
$var wire 16 2 res_g [15:0] $end
$var wire 16 3 res_h [15:0] $end
$var reg 16 4 BUF [15:0] $end
$var reg 16 5 CNT [15:0] $end
$var reg 16 6 ITERATIONS [15:0] $end
$var reg 1 7 RD $end
$var reg 16 8 RES [15:0] $end
$var reg 1 9 STold $end
$var reg 1 : rd_g_old $end
$var reg 1 ; rd_h_old $end
$var reg 1 < st_h $end
$var reg 1 = st_h_f $end
$scope module g $end
$var wire 1 ! CLK $end
$var wire 16 > IN0 [15:0] $end
$var wire 16 ? IN1 [15:0] $end
$var wire 1 & RST $end
$var wire 1 ' ST $end
$var reg 1 @ RD $end
$var reg 16 A RES [15:0] $end
$var reg 1 B RF $end
$var reg 1 C STold $end
$upscope $end
$scope module h $end
$var wire 1 ! CLK $end
$var wire 16 D IN0 [15:0] $end
$var wire 16 E IN1 [15:0] $end
$var wire 16 F IN2 [15:0] $end
$var wire 1 1 RD $end
$var wire 16 G RES [15:0] $end
$var wire 1 & RST $end
$var wire 1 H ST $end
$scope module summa $end
$var wire 1 ! CLK $end
$var wire 16 I IN0 [15:0] $end
$var wire 16 J IN1 [15:0] $end
$var wire 16 K IN2 [15:0] $end
$var wire 1 & RST $end
$var wire 1 H ST $end
$var wire 1 L rd_g $end
$var wire 1 M rd_h $end
$var wire 16 N res_g [15:0] $end
$var wire 16 O res_h [15:0] $end
$var reg 16 P BUF [15:0] $end
$var reg 16 Q CNT [15:0] $end
$var reg 16 R ITERATIONS [15:0] $end
$var reg 1 S RD $end
$var reg 16 T RES [15:0] $end
$var reg 1 U STold $end
$var reg 1 V rd_g_old $end
$var reg 1 W rd_h_old $end
$var reg 1 X st_h $end
$var reg 1 Y st_h_f $end
$scope module g $end
$var wire 1 ! CLK $end
$var wire 16 Z IN0 [15:0] $end
$var wire 16 [ IN1 [15:0] $end
$var wire 1 & RST $end
$var wire 1 H ST $end
$var reg 1 \ RD $end
$var reg 16 ] RES [15:0] $end
$var reg 1 ^ RF $end
$var reg 1 _ STold $end
$upscope $end
$scope module h $end
$var wire 1 ! CLK $end
$var wire 16 ` IN0 [15:0] $end
$var wire 16 a IN1 [15:0] $end
$var wire 16 b IN2 [15:0] $end
$var wire 1 M RD $end
$var wire 1 c RDi $end
$var wire 16 d RES [15:0] $end
$var wire 16 e RESi [15:0] $end
$var wire 1 & RST $end
$var wire 1 f ST $end
$scope module opi3 $end
$var wire 1 ! CLK $end
$var wire 16 g IN0 [15:0] $end
$var wire 16 h IN1 [15:0] $end
$var wire 16 i IN2 [15:0] $end
$var wire 1 & RST $end
$var wire 1 f ST $end
$var reg 1 j RD $end
$var reg 16 k RES [15:0] $end
$var reg 1 l RF $end
$var reg 1 m STold $end
$upscope $end
$scope module soperation $end
$var wire 1 ! CLK $end
$var wire 16 n IN [15:0] $end
$var wire 1 & RST $end
$var wire 1 c ST $end
$var reg 1 o RD $end
$var reg 16 p RES [15:0] $end
$var reg 1 q RF $end
$var reg 1 r STold $end
$upscope $end
$upscope $end
$upscope $end
$upscope $end
$upscope $end
$upscope $end
$scope module operation_i_bw16_inc2_si0 $end
$var wire 1 s CLK $end
$var wire 16 t IN0 [15:0] $end
$var wire 16 u IN1 [15:0] $end
$var wire 1 v RST $end
$var wire 1 w ST $end
$var reg 1 x RD $end
$var reg 16 y RES [15:0] $end
$var reg 1 z RF $end
$var reg 1 { STold $end
$upscope $end
$enddefinitions $end
#0
$dumpvars
x{
xz
bx y
xx
zw
zv
bz u
bz t
zs
xr
xq
bx p
xo
bx n
xm
xl
bx k
xj
bx i
bx h
b100 g
xf
bx e
bx d
xc
bx b
bx a
b100 `
x_
x^
bx ]
x\
b100 [
bx Z
xY
xX
xW
xV
xU
bx T
xS
bx R
bx Q
bx P
bx O
bx N
xM
xL
bx K
bx J
b100 I
xH
bx G
bx F
b101 E
b100 D
xC
xB
bx A
x@
b101 ?
b100 >
x=
x<
x;
x:
x9
bx 8
x7
bx 6
bx 5
bx 4
bx 3
bx 2
x1
x0
bx /
b101 .
b100 -
0,
1+
b101 *
b100 )
0(
0'
1&
bx %
x$
b101 #
b100 "
0!
$end
#5
0C
1@
10
0_
1^
1\
1L
0m
1l
1j
1c
1q
1o
1M
0X
0f
0Y
xW
xV
0U
b0 Q
1S
11
0<
0H
0=
x;
x:
09
b0 5
17
1$
1(
1!
#10
0(
0!
#15
1;
1:
1W
1V
1r
1(
1!
0+
0&
#20
0(
0!
#25
1C
0B
0@
00
19
b110 6
07
0$
1(
1!
1,
1'
#30
0(
0!
#35
b0 /
b0 F
b0 J
b0 Z
b0 a
b0 h
0:
09
0C
1B
b0 A
b0 2
1(
1!
0,
0'
#40
0(
0!
#45
1@
10
1(
1!
#50
0(
0!
#55
1:
1<
1H
1=
b0 4
1(
1!
#60
0(
0!
#65
1_
0^
0\
0L
1U
b0 R
0S
01
0=
1(
1!
#70
0(
0!
#75
b100 K
b100 b
b100 i
0;
0<
0H
0V
1^
b100 ]
b100 N
1(
1!
#80
0(
0!
#85
0_
1\
1L
0U
1(
1!
#90
0(
0!
#95
1;
1<
1H
1=
b1 5
b100 4
1V
b100 T
b100 3
b100 G
1S
11
1(
1!
#100
0(
0!
#105
1_
0^
0\
0L
1U
0S
01
0=
1(
1!
#110
0(
0!
#115
0;
0<
0H
0V
1^
1(
1!
#120
0(
0!
#125
0_
1\
1L
0U
1(
1!
#130
0(
0!
#135
b100 /
b100 F
b100 J
b100 Z
b100 a
b100 h
1;
1<
1H
1=
b10 5
1V
1S
11
1(
1!
#140
0(
0!
#145
1_
0^
0\
0L
1U
b101 R
0S
01
0=
1(
1!
#150
0(
0!
#155
0;
0<
0H
0V
1^
1(
1!
#160
0(
0!
#165
0_
1\
1L
0U
1(
1!
#170
0(
0!
#175
1V
1X
1f
1Y
b100 P
1(
1!
#180
0(
0!
#185
1m
0j
0c
0l
0Y
1(
1!
#190
0(
0!
#195
0X
0f
0r
1l
b100 k
b100 e
b100 n
1(
1!
#200
0(
0!
#205
0m
1j
1c
1(
1!
#210
0(
0!
#215
0W
1r
0o
0M
0q
1(
1!
#220
0(
0!
#225
1q
b101 p
b101 O
b101 d
1(
1!
#230
0(
0!
#235
1W
1X
1f
1Y
b1 Q
b101 P
1o
1M
1(
1!
#240
0(
0!
#245
1m
0j
0c
0l
0Y
1(
1!
#250
0(
0!
#255
0X
0f
0r
1l
1(
1!
#260
0(
0!
#265
0m
1j
1c
1(
1!
#270
0(
0!
#275
0W
1r
0o
0M
0q
1(
1!
#280
0(
0!
#285
1q
1(
1!
#290
0(
0!
#295
b101 K
b101 b
b101 i
1W
1X
1f
1Y
b10 Q
1o
1M
1(
1!
#300
0(
0!
#305
1m
0j
0c
0l
0Y
1(
1!
#310
0(
0!
#315
0X
0f
0r
1l
b101 k
b101 e
b101 n
1(
1!
#320
0(
0!
#325
0m
1j
1c
1(
1!
#330
0(
0!
#335
0W
1r
0o
0M
0q
1(
1!
#340
0(
0!
#345
b110 K
b110 b
b110 i
1q
b110 p
b110 O
b110 d
1(
1!
#350
0(
0!
#355
1W
1X
1f
1Y
b11 Q
b110 P
1o
1M
1(
1!
#360
0(
0!
#365
1m
0j
0c
0l
0Y
1(
1!
#370
0(
0!
#375
0X
0f
0r
1l
b110 k
b110 e
b110 n
1(
1!
#380
0(
0!
#385
0m
1j
1c
1(
1!
#390
0(
0!
#395
0W
1r
0o
0M
0q
1(
1!
#400
0(
0!
#405
b111 K
b111 b
b111 i
1q
b111 p
b111 O
b111 d
1(
1!
#410
0(
0!
#415
1W
1X
1f
1Y
b100 Q
b111 P
1o
1M
1(
1!
#420
0(
0!
#425
1m
0j
0c
0l
0Y
1(
1!
#430
0(
0!
#435
0X
0f
0r
1l
b111 k
b111 e
b111 n
1(
1!
#440
0(
0!
#445
0m
1j
1c
1(
1!
#450
0(
0!
#455
0W
1r
0o
0M
0q
1(
1!
#460
0(
0!
#465
b1000 K
b1000 b
b1000 i
1q
b1000 p
b1000 O
b1000 d
1(
1!
#470
0(
0!
#475
1W
1X
1f
1Y
b101 Q
b1000 P
1o
1M
1(
1!
#480
0(
0!
#485
b1000 /
b1000 F
b1000 J
b1000 Z
b1000 a
b1000 h
b100 K
b100 b
b100 i
b1000 T
b1000 3
b1000 G
0Y
0X
0f
b0 Q
1S
11
1(
1!
#490
0(
0!
#495
1;
1<
1H
1=
b11 5
b1000 4
1(
1!
#500
0(
0!
#505
1_
0^
0\
0L
1U
b1001 R
0S
01
0=
1(
1!
#510
0(
0!
#515
0;
0<
0H
0V
1^
1(
1!
#520
0(
0!
#525
0_
1\
1L
0U
1(
1!
#530
0(
0!
#535
1V
1X
1f
1Y
b100 P
1(
1!
#540
0(
0!
#545
1m
0j
0c
0l
0Y
1(
1!
#550
0(
0!
#555
0X
0f
0r
1l
b100 k
b100 e
b100 n
1(
1!
#560
0(
0!
#565
0m
1j
1c
1(
1!
#570
0(
0!
#575
0W
1r
0o
0M
0q
1(
1!
#580
0(
0!
#585
1q
b101 p
b101 O
b101 d
1(
1!
#590
0(
0!
#595
1W
1X
1f
1Y
b1 Q
b101 P
1o
1M
1(
1!
#600
0(
0!
#605
1m
0j
0c
0l
0Y
1(
1!
#610
0(
0!
#615
0X
0f
0r
1l
1(
1!
#620
0(
0!
#625
0m
1j
1c
1(
1!
#630
0(
0!
#635
0W
1r
0o
0M
0q
1(
1!
#640
0(
0!
#645
1q
1(
1!
#650
0(
0!
#655
b101 K
b101 b
b101 i
1W
1X
1f
1Y
b10 Q
1o
1M
1(
1!
#660
0(
0!
#665
1m
0j
0c
0l
0Y
1(
1!
#670
0(
0!
#675
0X
0f
0r
1l
b101 k
b101 e
b101 n
1(
1!
#680
0(
0!
#685
0m
1j
1c
1(
1!
#690
0(
0!
#695
0W
1r
0o
0M
0q
1(
1!
#700
0(
0!
#705
b110 K
b110 b
b110 i
1q
b110 p
b110 O
b110 d
1(
1!
#710
0(
0!
#715
1W
1X
1f
1Y
b11 Q
b110 P
1o
1M
1(
1!
#720
0(
0!
#725
1m
0j
0c
0l
0Y
1(
1!
#730
0(
0!
#735
0X
0f
0r
1l
b110 k
b110 e
b110 n
1(
1!
#740
0(
0!
#745
0m
1j
1c
1(
1!
#750
0(
0!
#755
0W
1r
0o
0M
0q
1(
1!
#760
0(
0!
#765
b111 K
b111 b
b111 i
1q
b111 p
b111 O
b111 d
1(
1!
#770
0(
0!
#775
1W
1X
1f
1Y
b100 Q
b111 P
1o
1M
1(
1!
#780
0(
0!
#785
1m
0j
0c
0l
0Y
1(
1!
#790
0(
0!
#795
0X
0f
0r
1l
b111 k
b111 e
b111 n
1(
1!
#800
0(
0!
#805
0m
1j
1c
1(
1!
#810
0(
0!
#815
0W
1r
0o
0M
0q
1(
1!
#820
0(
0!
#825
b1000 K
b1000 b
b1000 i
1q
b1000 p
b1000 O
b1000 d
1(
1!
#830
0(
0!
#835
1W
1X
1f
1Y
b101 Q
b1000 P
1o
1M
1(
1!
#840
0(
0!
#845
1m
0j
0c
0l
0Y
1(
1!
#850
0(
0!
#855
0X
0f
0r
1l
b1000 k
b1000 e
b1000 n
1(
1!
#860
0(
0!
#865
0m
1j
1c
1(
1!
#870
0(
0!
#875
0W
1r
0o
0M
0q
1(
1!
#880
0(
0!
#885
b1001 K
b1001 b
b1001 i
1q
b1001 p
b1001 O
b1001 d
1(
1!
#890
0(
0!
#895
1W
1X
1f
1Y
b110 Q
b1001 P
1o
1M
1(
1!
#900
0(
0!
#905
1m
0j
0c
0l
0Y
1(
1!
#910
0(
0!
#915
0X
0f
0r
1l
b1001 k
b1001 e
b1001 n
1(
1!
#920
0(
0!
#925
0m
1j
1c
1(
1!
#930
0(
0!
#935
0W
1r
0o
0M
0q
1(
1!
#940
0(
0!
#945
b1010 K
b1010 b
b1010 i
1q
b1010 p
b1010 O
b1010 d
1(
1!
#950
0(
0!
#955
1W
1X
1f
1Y
b111 Q
b1010 P
1o
1M
1(
1!
#960
0(
0!
#965
1m
0j
0c
0l
0Y
1(
1!
#970
0(
0!
#975
0X
0f
0r
1l
b1010 k
b1010 e
b1010 n
1(
1!
#980
0(
0!
#985
0m
1j
1c
1(
1!
#990
0(
0!
#995
0W
1r
0o
0M
0q
1(
1!
#1000
0(
0!
#1005
b1011 K
b1011 b
b1011 i
1q
b1011 p
b1011 O
b1011 d
1(
1!
#1010
0(
0!
#1015
1W
1X
1f
1Y
b1000 Q
b1011 P
1o
1M
1(
1!
#1020
0(
0!
#1025
1m
0j
0c
0l
0Y
1(
1!
#1030
0(
0!
#1035
0X
0f
0r
1l
b1011 k
b1011 e
b1011 n
1(
1!
#1040
0(
0!
#1045
0m
1j
1c
1(
1!
#1050
0(
0!
#1055
0W
1r
0o
0M
0q
1(
1!
#1060
0(
0!
#1065
b1100 K
b1100 b
b1100 i
1q
b1100 p
b1100 O
b1100 d
1(
1!
#1070
0(
0!
#1075
1W
1X
1f
1Y
b1001 Q
b1100 P
1o
1M
1(
1!
#1080
0(
0!
#1085
b1100 /
b1100 F
b1100 J
b1100 Z
b1100 a
b1100 h
b100 K
b100 b
b100 i
b1100 T
b1100 3
b1100 G
0Y
0X
0f
b0 Q
1S
11
1(
1!
#1090
0(
0!
#1095
1;
1<
1H
1=
b100 5
b1100 4
1(
1!
#1100
0(
0!
#1105
1_
0^
0\
0L
1U
b1101 R
0S
01
0=
1(
1!
#1110
0(
0!
#1115
0;
0<
0H
0V
1^
1(
1!
#1120
0(
0!
#1125
0_
1\
1L
0U
1(
1!
#1130
0(
0!
#1135
1V
1X
1f
1Y
b100 P
1(
1!
#1140
0(
0!
#1145
1m
0j
0c
0l
0Y
1(
1!
#1150
0(
0!
#1155
0X
0f
0r
1l
b100 k
b100 e
b100 n
1(
1!
#1160
0(
0!
#1165
0m
1j
1c
1(
1!
#1170
0(
0!
#1175
0W
1r
0o
0M
0q
1(
1!
#1180
0(
0!
#1185
1q
b101 p
b101 O
b101 d
1(
1!
#1190
0(
0!
#1195
1W
1X
1f
1Y
b1 Q
b101 P
1o
1M
1(
1!
#1200
0(
0!
#1205
1m
0j
0c
0l
0Y
1(
1!
#1210
0(
0!
#1215
0X
0f
0r
1l
1(
1!
#1220
0(
0!
#1225
0m
1j
1c
1(
1!
#1230
0(
0!
#1235
0W
1r
0o
0M
0q
1(
1!
#1240
0(
0!
#1245
1q
1(
1!
#1250
0(
0!
#1255
b101 K
b101 b
b101 i
1W
1X
1f
1Y
b10 Q
1o
1M
1(
1!
#1260
0(
0!
#1265
1m
0j
0c
0l
0Y
1(
1!
#1270
0(
0!
#1275
0X
0f
0r
1l
b101 k
b101 e
b101 n
1(
1!
#1280
0(
0!
#1285
0m
1j
1c
1(
1!
#1290
0(
0!
#1295
0W
1r
0o
0M
0q
1(
1!
#1300
0(
0!
#1305
b110 K
b110 b
b110 i
1q
b110 p
b110 O
b110 d
1(
1!
#1310
0(
0!
#1315
1W
1X
1f
1Y
b11 Q
b110 P
1o
1M
1(
1!
#1320
0(
0!
#1325
1m
0j
0c
0l
0Y
1(
1!
#1330
0(
0!
#1335
0X
0f
0r
1l
b110 k
b110 e
b110 n
1(
1!
#1340
0(
0!
#1345
0m
1j
1c
1(
1!
#1350
0(
0!
#1355
0W
1r
0o
0M
0q
1(
1!
#1360
0(
0!
#1365
b111 K
b111 b
b111 i
1q
b111 p
b111 O
b111 d
1(
1!
#1370
0(
0!
#1375
1W
1X
1f
1Y
b100 Q
b111 P
1o
1M
1(
1!
#1380
0(
0!
#1385
1m
0j
0c
0l
0Y
1(
1!
#1390
0(
0!
#1395
0X
0f
0r
1l
b111 k
b111 e
b111 n
1(
1!
#1400
0(
0!
#1405
0m
1j
1c
1(
1!
#1410
0(
0!
#1415
0W
1r
0o
0M
0q
1(
1!
#1420
0(
0!
#1425
b1000 K
b1000 b
b1000 i
1q
b1000 p
b1000 O
b1000 d
1(
1!
#1430
0(
0!
#1435
1W
1X
1f
1Y
b101 Q
b1000 P
1o
1M
1(
1!
#1440
0(
0!
#1445
1m
0j
0c
0l
0Y
1(
1!
#1450
0(
0!
#1455
0X
0f
0r
1l
b1000 k
b1000 e
b1000 n
1(
1!
#1460
0(
0!
#1465
0m
1j
1c
1(
1!
#1470
0(
0!
#1475
0W
1r
0o
0M
0q
1(
1!
#1480
0(
0!
#1485
b1001 K
b1001 b
b1001 i
1q
b1001 p
b1001 O
b1001 d
1(
1!
#1490
0(
0!
#1495
1W
1X
1f
1Y
b110 Q
b1001 P
1o
1M
1(
1!
#1500
0(
0!
#1505
1m
0j
0c
0l
0Y
1(
1!
#1510
0(
0!
#1515
0X
0f
0r
1l
b1001 k
b1001 e
b1001 n
1(
1!
#1520
0(
0!
#1525
0m
1j
1c
1(
1!
#1530
0(
0!
#1535
0W
1r
0o
0M
0q
1(
1!
#1540
0(
0!
#1545
b1010 K
b1010 b
b1010 i
1q
b1010 p
b1010 O
b1010 d
1(
1!
#1550
0(
0!
#1555
1W
1X
1f
1Y
b111 Q
b1010 P
1o
1M
1(
1!
#1560
0(
0!
#1565
1m
0j
0c
0l
0Y
1(
1!
#1570
0(
0!
#1575
0X
0f
0r
1l
b1010 k
b1010 e
b1010 n
1(
1!
#1580
0(
0!
#1585
0m
1j
1c
1(
1!
#1590
0(
0!
#1595
0W
1r
0o
0M
0q
1(
1!
#1600
0(
0!
#1605
b1011 K
b1011 b
b1011 i
1q
b1011 p
b1011 O
b1011 d
1(
1!
#1610
0(
0!
#1615
1W
1X
1f
1Y
b1000 Q
b1011 P
1o
1M
1(
1!
#1620
0(
0!
#1625
1m
0j
0c
0l
0Y
1(
1!
#1630
0(
0!
#1635
0X
0f
0r
1l
b1011 k
b1011 e
b1011 n
1(
1!
#1640
0(
0!
#1645
0m
1j
1c
1(
1!
#1650
0(
0!
#1655
0W
1r
0o
0M
0q
1(
1!
#1660
0(
0!
#1665
b1100 K
b1100 b
b1100 i
1q
b1100 p
b1100 O
b1100 d
1(
1!
#1670
0(
0!
#1675
1W
1X
1f
1Y
b1001 Q
b1100 P
1o
1M
1(
1!
#1680
0(
0!
#1685
1m
0j
0c
0l
0Y
1(
1!
#1690
0(
0!
#1695
0X
0f
0r
1l
b1100 k
b1100 e
b1100 n
1(
1!
#1700
0(
0!
#1705
0m
1j
1c
1(
1!
#1710
0(
0!
#1715
0W
1r
0o
0M
0q
1(
1!
#1720
0(
0!
#1725
b1101 K
b1101 b
b1101 i
1q
b1101 p
b1101 O
b1101 d
1(
1!
#1730
0(
0!
#1735
1W
1X
1f
1Y
b1010 Q
b1101 P
1o
1M
1(
1!
#1740
0(
0!
#1745
1m
0j
0c
0l
0Y
1(
1!
#1750
0(
0!
#1755
0X
0f
0r
1l
b1101 k
b1101 e
b1101 n
1(
1!
#1760
0(
0!
#1765
0m
1j
1c
1(
1!
#1770
0(
0!
#1775
0W
1r
0o
0M
0q
1(
1!
#1780
0(
0!
#1785
b1110 K
b1110 b
b1110 i
1q
b1110 p
b1110 O
b1110 d
1(
1!
#1790
0(
0!
#1795
1W
1X
1f
1Y
b1011 Q
b1110 P
1o
1M
1(
1!
#1800
0(
0!
#1805
1m
0j
0c
0l
0Y
1(
1!
#1810
0(
0!
#1815
0X
0f
0r
1l
b1110 k
b1110 e
b1110 n
1(
1!
#1820
0(
0!
#1825
0m
1j
1c
1(
1!
#1830
0(
0!
#1835
0W
1r
0o
0M
0q
1(
1!
#1840
0(
0!
#1845
b1111 K
b1111 b
b1111 i
1q
b1111 p
b1111 O
b1111 d
1(
1!
#1850
0(
0!
#1855
1W
1X
1f
1Y
b1100 Q
b1111 P
1o
1M
1(
1!
#1860
0(
0!
